nagaagent_core/__init__.py
nagaagent_core/cli.py
nagaagent_core/qt.py
nagaagent_core/api/__init__.py
nagaagent_core/core/__init__.py
nagaagent_core/vendors/__init__.py
nagaagent_core/vendors/agents.py
nagaagent_core/vendors/cv2.py
nagaagent_core/vendors/html2text.py
nagaagent_core/vendors/httpx.py
nagaagent_core/vendors/numpy.py
nagaagent_core/vendors/paho_mqtt.py
nagaagent_core/vendors/pandas.py
nagaagent_core/vendors/pil.py
nagaagent_core/vendors/playwright.py
nagaagent_core/vendors/pyautogui.py
nagaagent_core/vendors/pydantic.py
nagaagent_core/vendors/pygame.py
nagaagent_core/vendors/pytesseract.py
nagaagent_core/vendors/scipy.py
nagaagent_core/vendors/transformers.py
nagaagent_core/vendors/PyQt5/QtCore.py
nagaagent_core/vendors/PyQt5/QtGui.py
nagaagent_core/vendors/PyQt5/QtOpenGL.py
nagaagent_core/vendors/PyQt5/QtWidgets.py
nagaagent_core/vendors/PyQt5/__init__.py
nagaagent_core/vendors/pycaw/__init__.py
nagaagent_core-1.0.6.dist-info/licenses/LICENSE
nagaagent_core-1.0.6.dist-info/METADATA
nagaagent_core-1.0.6.dist-info/WHEEL
nagaagent_core-1.0.6.dist-info/entry_points.txt
nagaagent_core-1.0.6.dist-info/top_level.txt
nagaagent_core-1.0.6.dist-info/RECORD
