Metadata-Version: 2.4
Name: nagaagent-core
Version: 1.0.6
Summary: NagaAgent核心依赖包，包含核心功能和API服务器相关依赖
Home-page: https://github.com/nagaagent/nagaagent-core
Author: NagaAgent Team
Author-email: NagaAgent Team <nagaagent@example.com>
License: MIT
Classifier: Development Status :: 4 - Beta
Classifier: Intended Audience :: Developers
Classifier: License :: OSI Approved :: MIT License
Classifier: Operating System :: OS Independent
Classifier: Programming Language :: Python :: 3
Classifier: Programming Language :: Python :: 3.8
Classifier: Programming Language :: Python :: 3.9
Classifier: Programming Language :: Python :: 3.10
Classifier: Programming Language :: Python :: 3.11
Classifier: Programming Language :: Python :: 3.12
Requires-Python: >=3.8
License-File: LICENSE
Requires-Dist: mcp>=1.6.0
Requires-Dist: openai>=1.76.0
Requires-Dist: python-dotenv>=1.1.0
Requires-Dist: requests>=2.32.3
Requires-Dist: aiohttp>=3.11.18
Requires-Dist: flask>=3.1.0
Requires-Dist: gevent>=25.5.1
Requires-Dist: fastapi>=0.115.0
Requires-Dist: uvicorn[standard]>=0.34.0
Requires-Dist: PyQt5>=5.15.11
Requires-Dist: pyqt5-qt5>=5.15.2
Requires-Dist: pyqt5-sip>=12.17.0
Requires-Dist: psutil>=5.9.0
Requires-Dist: py2neo>=2021.2.3
Requires-Dist: pyvis>=0.3.2
Requires-Dist: matplotlib>=3.10.0
Requires-Dist: neo4j
Requires-Dist: librosa
Requires-Dist: accelerate
Requires-Dist: torch
Requires-Dist: pycaw>=20240210
Requires-Dist: comtypes>=1.2.0
Requires-Dist: screen-brightness-control>=0.21.0
Requires-Dist: sounddevice>=0.4.6
Requires-Dist: pyaudio>=0.2.14
Requires-Dist: edge-tts>=7.0.2
Requires-Dist: emoji>=2.8.0
Requires-Dist: pystray>=0.19.4
Requires-Dist: jmcomic>=2.6.5
Requires-Dist: fastmcp>=2.11.2
Requires-Dist: paho-mqtt>=2.0.0
Requires-Dist: tiktoken
Requires-Dist: python-docx>=1.2.0
Requires-Dist: onnxruntime
Requires-Dist: live2d-py>=0.5.4
Requires-Dist: PyOpenGL>=3.1.0
Requires-Dist: toml>=0.10.2
Requires-Dist: opensimplex>=0.4.5.1
Requires-Dist: langchain-community>=0.3.29
Requires-Dist: playwright>=1.52.0
Requires-Dist: bilibili-api-python
Requires-Dist: langchain-openai>=0.3.34
Requires-Dist: crawl4ai>=0.7.4
Requires-Dist: pyautogui>=0.9.54
Requires-Dist: gui-agents>=0.3.0
Requires-Dist: paddleocr>=3.1.0
Requires-Dist: pytesseract>=0.3.13
Requires-Dist: opencv-python>=4.12.0.88
Requires-Dist: opencv-contrib-python>=4.10.0.84
Requires-Dist: pygetwindow>=0.0.9
Requires-Dist: pywinauto>=0.6.9
Requires-Dist: Pillow>=11.3.0
Requires-Dist: numpy>=1.26.4
Provides-Extra: dev
Requires-Dist: pytest>=6.0; extra == "dev"
Requires-Dist: pytest-asyncio>=0.21.0; extra == "dev"
Requires-Dist: black>=22.0; extra == "dev"
Requires-Dist: flake8>=4.0; extra == "dev"
Dynamic: author
Dynamic: home-page
Dynamic: license-file
Dynamic: requires-python
